ssd.v
module ssd (
    input [3:0] digit,     // 4-bit input digit
    output reg [7:0] pgfedcba // SSD control signals
);
    always @(*) begin
        case (digit)
            4'd0: pgfedcba = 8'b00111111; // 0
            4'd1: pgfedcba = 8'b00000110; // 1
            4'd2: pgfedcba = 8'b01011011; // 2
            4'd3: pgfedcba = 8'b01001111; // 3
            4'd4: pgfedcba = 8'b01100110; // 4
            4'd5: pgfedcba = 8'b01101101; // 5
            4'd6: pgfedcba = 8'b01111101; // 6
            4'd7: pgfedcba = 8'b00000111; // 7
            4'd8: pgfedcba = 8'b01111111; // 8
            4'd9: pgfedcba = 8'b01101111; // 9
            default: pgfedcba = 8'b00000000; // Blank
        endcase
    end
endmodule

ssd.tb.v
`timescale 1ns / 1ps

module ssd_tb;
    reg [3:0] digit;       // Test input (digit)
    wire [7:0] pgfedcba;   // Test output (SSD control signals)

    // Instantiate the SSD module
    ssd uut (
        .digit(digit),
        .pgfedcba(pgfedcba)
    );

    // Apply test cases
    initial begin
        $monitor("Time: %0d, Digit: %b, SSD Output: %b", $time, digit, pgfedcba);
        $dumpfile("ssd_tb.vcd");
        $dumpvars(0, ssd_tb);

        digit = 4'd0; #10;
        digit = 4'd1; #10;
        digit = 4'd2; #10;
        digit = 4'd3; #10;
        digit = 4'd4; #10;
        digit = 4'd5; #10;
        digit = 4'd6; #10;
        digit = 4'd7; #10;
        digit = 4'd8; #10;
        digit = 4'd9; #10;
        $finish;
    end
endmodule

ssd_tb.vcd
$date
	Sun Dec 15 03:20:27 2024
$end
$version
	Icarus Verilog
$end
$timescale
	1ps
$end
$scope module ssd_tb $end
$var wire 8 ! pgfedcba [7:0] $end
$var reg 4 " digit [3:0] $end
$scope module uut $end
$var wire 4 # digit [3:0] $end
$var reg 8 $ pgfedcba [7:0] $end
$upscope $end
$upscope $end
$enddefinitions $end
$comment Show the parameter values. $end
$dumpall
$end
#0
$dumpvars
b111111 $
b0 #
b0 "
b111111 !
$end
#10000
b110 !
b110 $
b1 "
b1 #
#20000
b1011011 !
b1011011 $
b10 "
b10 #
#30000
b1001111 !
b1001111 $
b11 "
b11 #
#40000
b1100110 !
b1100110 $
b100 "
b100 #
#50000
b1101101 !
b1101101 $
b101 "
b101 #
#60000
b1111101 !
b1111101 $
b110 "
b110 #
#70000
b111 !
b111 $
b111 "
b111 #
#80000
b1111111 !
b1111111 $
b1000 "
b1000 #
#90000
b1101111 !
b1101111 $
b1001 "
b1001 #
